posi/__init__.py
posi/main.py
posi-7.0.6.dist-info/LICENSE
posi-7.0.6.dist-info/METADATA
posi-7.0.6.dist-info/WHEEL
posi-7.0.6.dist-info/top_level.txt
posi-7.0.6.dist-info/RECORD
