Metadata-Version: 2.1
Name: posi
Version: 7.0.6
Summary: A demo package. Bugbounty.
Home-page: https://github.com/Neiroline/posi
Author: Amelio
Author-email: jiznetoigra@gmail.com
Project-URL: Bug Tracker, https://github.com/Neiroline/posi/issues
Classifier: Programming Language :: Python :: 3
Classifier: License :: OSI Approved :: MIT License
Classifier: Operating System :: OS Independent
Requires-Python: >=3.6
License-File: LICENSE
